elenchos_check_cpu/CheckCpuCommand.py
elenchos_check_cpu/CheckCpuPlugin.py
elenchos_check_cpu/__init__.py
elenchos_check_cpu/commands.xml
elenchos_check_cpu-1.1.0.dist-info/LICENSE.md
elenchos_check_cpu-1.1.0.dist-info/METADATA
elenchos_check_cpu-1.1.0.dist-info/WHEEL
elenchos_check_cpu-1.1.0.dist-info/RECORD
