Metadata-Version: 2.3
Name: elenchos_check_cpu
Version: 1.1.0
Summary: A Élenchos command for checking CPU usage.
License: MIT
Keywords: Élenchos,Elenchos,CPU
Author: Set Based IT Consultancy
Author-email: info@setbased.nl
Requires-Python: >=3.12.0,<4.0.0
Classifier: Development Status :: 5 - Production/Stable
Classifier: Intended Audience :: System Administrators
Classifier: License :: OSI Approved :: MIT License
Classifier: Programming Language :: Python :: 3
Classifier: Programming Language :: Python :: 3.12
Classifier: Programming Language :: Python :: 3.13
Classifier: Topic :: System :: Systems Administration
Requires-Dist: elenchos (>=1.2.0,<2.0.0)
Project-URL: Documentation, https://github.com/NagiosElenchos/check_cpu
Project-URL: Repository, https://github.com/NagiosElenchos/check_cpu
